<mujoco>
    <actuator>
        <general group="1" name="LBicepsLongus" class="muscle" tendon="LBicepsLongus_tendon"   ctrlrange="0 1" lengthrange="0.013335 0.024965" actdim="1" dyntype="muscle" gaintype="muscle" gainprm="0.5 1.5 0.78 1 0.5 1.6 10 1.3 1.2 0" biastype="muscle" biasprm="0.75 1.05 -1 200 0.5 1.6 1.5 1.3 1.2 0" />
        <general group="1" name="LBicepsBrevis" class="muscle" tendon="LBicepsBrevis_tendon"   ctrlrange="0 1" lengthrange="0.01061 0.01969" actdim="1" dyntype="muscle" gaintype="muscle" gainprm="0.5 1.5 0.84 1 0.5 1.6 10 1.3 1.2 0" biastype="muscle" biasprm="0.75 1.05 -1 200 0.5 1.6 1.5 1.3 1.2 0" />
        <general group="1" name="LTri_Long" class="muscle" tendon="LTri_Long_tendon"   ctrlrange="0 1" lengthrange="0.008385 0.015395" actdim="1" dyntype="muscle" gaintype="muscle" gainprm="0.5 1.5 4.65 1 0.5 1.6 10 1.3 1.2 0" biastype="muscle" biasprm="0.75 1.05 -1 200 0.5 1.6 1.5 1.3 1.2 0" />
        <general group="1" name="LTri_Lateral" class="muscle" tendon="LTri_Lateral_tendon"   ctrlrange="0 1" lengthrange="0.008615 0.016785" actdim="1" dyntype="muscle" gaintype="muscle" gainprm="0.5 1.5 0.71 1 0.5 1.6 10 1.3 1.2 0" biastype="muscle" biasprm="0.75 1.05 -1 200 0.5 1.6 1.5 1.3 1.2 0" />
        <general group="1" name="LTri_Medial" class="muscle" tendon="LTri_Medial_tendon"   ctrlrange="0 1" lengthrange="0.008895 0.013825" actdim="1" dyntype="muscle" gaintype="muscle" gainprm="0.5 1.5 0.45 1 0.5 1.6 10 1.3 1.2 0" biastype="muscle" biasprm="0.75 1.05 -1 200 0.5 1.6 1.5 1.3 1.2 0" />
        <general group="1" name="LBrachialis" class="muscle" tendon="LBrachialis_tendon"   ctrlrange="0 1" lengthrange="0.01061 0.02067" actdim="1" dyntype="muscle" gaintype="muscle" gainprm="0.5 1.5 0.25 1 0.5 1.6 10 1.3 1.2 0" biastype="muscle" biasprm="0.75 1.05 -1 200 0.5 1.6 1.5 1.3 1.2 0" />
        <general group="1" name="LAnconeus" class="muscle" tendon="LAnconeus_tendon"   ctrlrange="0 1" lengthrange="0.0022 0.00362" actdim="1" dyntype="muscle" gaintype="muscle" gainprm="0.5 1.5 0.15 1 0.5 1.6 10 1.3 1.2 0" biastype="muscle" biasprm="0.75 1.05 -1 200 0.5 1.6 1.5 1.3 1.2 0" />
        <general group="1" name="LCoracobrachialis" class="muscle" tendon="LCoracobrachialis_tendon"   ctrlrange="0 1" lengthrange="0.00723 0.01241" actdim="1" dyntype="muscle" gaintype="muscle" gainprm="0.5 1.5 0.28 1 0.5 1.6 10 1.3 1.2 0" biastype="muscle" biasprm="0.75 1.05 -1 200 0.5 1.6 1.5 1.3 1.2 0" />
        <general group="1" name="LPronatorTeres" class="muscle" tendon="LPronatorTeres_tendon"   ctrlrange="0 1" lengthrange="0.006335 0.009085" actdim="1" dyntype="muscle" gaintype="muscle" gainprm="0.5 1.5 0.55 1 0.5 1.6 10 1.3 1.2 0" biastype="muscle" biasprm="0.75 1.05 -1 200 0.5 1.6 1.5 1.3 1.2 0" />
        <general group="1" name="LFlaxorCarpiUlnar" class="muscle" tendon="LFlaxorCarpiUlnar_tendon"   ctrlrange="0 1" lengthrange="0.01443 0.02271" actdim="1" dyntype="muscle" gaintype="muscle" gainprm="0.5 1.5 0.69 1 0.5 1.6 10 1.3 1.2 0" biastype="muscle" biasprm="0.75 1.05 -1 200 0.5 1.6 1.5 1.3 1.2 0" />
        <general group="1" name="LPalmarLongus" class="muscle" tendon="LPalmarLongus_tendon"   ctrlrange="0 1" lengthrange="0.01457 0.02547" actdim="1" dyntype="muscle" gaintype="muscle" gainprm="0.5 1.5 0.27 1 0.5 1.6 10 1.3 1.2 0" biastype="muscle" biasprm="0.75 1.05 -1 200 0.5 1.6 1.5 1.3 1.2 0" />   
        <general group="1" name="LFlaxorCarpiRadialis" class="muscle" tendon="LFlaxorCarpiRadialis_tendon"   ctrlrange="0 1" lengthrange="0.0152 0.02412" actdim="1" dyntype="muscle" gaintype="muscle" gainprm="0.5 1.5 0.38 1 0.5 1.6 10 1.3 1.2 0" biastype="muscle" biasprm="0.75 1.05 -1 200 0.5 1.6 1.5 1.3 1.2 0" />
        
        <general group="1" name="LExtensorCarpiRadialisLongus" class="muscle" tendon="LExtensorCarpiRadialisLongus_tendon"   ctrlrange="0 1" lengthrange="0.01422 0.02808" actdim="1" dyntype="muscle" gaintype="muscle" gainprm="0.5 1.5 0.38 1 0.5 1.6 10 1.3 1.2 0" biastype="muscle" biasprm="0.75 1.05 -1 200 0.5 1.6 1.5 1.3 1.2 0" />
        <general group="1" name="LExtensorCarpiRadialisBrevis" class="muscle" tendon="LExtensorCarpiRadialisBrevis_tendon"   ctrlrange="0 1" lengthrange="0.014935 0.029385" actdim="1" dyntype="muscle" gaintype="muscle" gainprm="0.5 1.5 0.35 1 0.5 1.6 10 1.3 1.2 0" biastype="muscle" biasprm="0.75 1.05 -1 200 0.5 1.6 1.5 1.3 1.2 0" />     
        
        <general group="1" name="LExtensorCarpiUlnar" class="muscle" tendon="LExtensorCarpiUlnar_tendon"   ctrlrange="0 1" lengthrange="0.014675 0.022345" actdim="1" dyntype="muscle" gaintype="muscle" gainprm="0.5 1.5 0.52 1 0.5 1.6 10 1.3 1.2 0" biastype="muscle" biasprm="0.75 1.05 -1 200 0.5 1.6 1.5 1.3 1.2 0" />
    
    </actuator>
</mujoco>